news/__init__.py
news/apps/__init__.py
news/apps/communications_app.py
news/apps/mailing_lists_app.py
news/apps/preview_app.py
news/apps/subjects_app.py
news/apps/templates_app.py
news/apps/messages_app/__init__.py
news/apps/messages_app/message_form.py
news/apps/messages_app/messages_app.py
news/management/__init__.py
news/management/commands/__init__.py
news/management/commands/send_communications.py
news/migrations/0001_initial.py
news/migrations/0002_auto_20190807_2114.py
news/migrations/0003_auto_20190807_2125.py
news/migrations/0004_auto_20190807_2133.py
news/migrations/0005_mailinglist_reminder_template.py
news/migrations/0006_mailinglist_subject.py
news/migrations/0007_communication_messages.py
news/migrations/__init__.py
news/models/__init__.py
news/models/communication.py
news/models/mailing_list.py
news/models/message.py
news/models/subject.py
news/models/template.py
core_news-0.1.dist-info/METADATA
core_news-0.1.dist-info/WHEEL
core_news-0.1.dist-info/top_level.txt
core_news-0.1.dist-info/RECORD
