Metadata-Version: 2.1
Name: core-news
Version: 0.1
Summary: Research CORE ERM - news & events module
Home-page: https://github.com/research-core/core-news
Author: Ricardo Ribeiro, Hugo Cachitas
Author-email: ricardojvr@gmail.com, hugo.cachitas@research.fchampalimaud.org
License: MIT
Platform: UNKNOWN
